static_sox/__init__.py
static_sox/_add_paths.py
static_sox/cli.py
static_sox/py.typed
static_sox/run.py
static_sox-1.0.2.dist-info/METADATA
static_sox-1.0.2.dist-info/WHEEL
static_sox-1.0.2.dist-info/entry_points.txt
static_sox-1.0.2.dist-info/top_level.txt
static_sox-1.0.2.dist-info/RECORD
