Metadata-Version: 2.4
Name: static-sox
Version: 1.0.2
Summary: Static binaries for sox for Mac/Win32/Linux
Home-page: https://github.com/zackees/static-sox
Maintainer: Zachary Vorhies
License: BSD 3-Clause License
Keywords: template-python-cmd
Classifier: Programming Language :: Python :: 3
Requires-Python: >=3.7
Requires-Dist: requests
Requires-Dist: filelock
Dynamic: home-page
Dynamic: maintainer
